{
  "id": 10909115,
  "revision": 0,
  "ephemeral_state": false,
  "biome_tiles": {
    "tiles": [
      "000000000000000000000000000000",
      "000000000000000000000000000000",
      "066666666660000000000000000000",
      "066666666660000000000000000000",
      "066666666660000000000000000000",
      "066666666660000000000000000000",
      "066666666660000000000000000000",
      "066666666660000000000000000000",
      "000000000000000000000000000000"
    ],
    "sheet_id": 1002
  },
  "constructions_tiles": {
    "tiles": [
      "OOOOOOOOOOO0000000000000000000",
      "OOOOOOOOOOO0000000000000000000",
      "O00000000000000000000000000000",
      "O00000000000000000000000000000",
      "O00000000000000000000000000000",
      "O00000000000000000000000000000",
      "O00000000000000000000000000000",
      "O00000000000000000000000000000",
      "OOOOO00OOOO0000000000000000000"
    ],
    "sheet_id": 1003
  },
  "entities": [
    {
      "id": 10909118,
      "frame": {
        "x": 5,
        "y": 8,
        "w": 1,
        "h": 1
      },
      "species_id": 1019,
      "entity_type": "Teleporter",
      "direction": "Down",
      "current_speed": 0.0,
      "sprite": {
        "sheet_id": 1010,
        "frame": {
          "x": 7,
          "y": 5,
          "w": 1,
          "h": 1
        },
        "number_of_frames": 1
      },
      "dialogues": [],
      "destination": {
        "world": 1008,
        "x": 0,
        "y": 0,
        "direction": "Unknown"
      },
      "lock_type": "None",
      "display_conditions": [],
      "movement_directions": "None",
      "is_consumable": false,
      "contents": null,
      "is_invulnerable": true,
      "demands_attention": false,
      "after_dialogue": "Nothing"
    },
    {
      "id": 10909119,
      "frame": {
        "x": 6,
        "y": 8,
        "w": 1,
        "h": 1
      },
      "species_id": 1019,
      "entity_type": "Teleporter",
      "direction": "Down",
      "current_speed": 0.0,
      "sprite": {
        "sheet_id": 1010,
        "frame": {
          "x": 7,
          "y": 5,
          "w": 1,
          "h": 1
        },
        "number_of_frames": 1
      },
      "dialogues": [],
      "destination": {
        "world": 1008,
        "x": 0,
        "y": 0,
        "direction": "Unknown"
      },
      "lock_type": "None",
      "display_conditions": [],
      "movement_directions": "None",
      "is_consumable": false,
      "contents": null,
      "is_invulnerable": true,
      "demands_attention": false,
      "after_dialogue": "Nothing"
    },
    {
      "id": 10909120,
      "frame": {
        "x": 8,
        "y": 0,
        "w": 1,
        "h": 2
      },
      "species_id": 1010,
      "entity_type": "StaticObject",
      "direction": "Down",
      "current_speed": 0.0,
      "sprite": {
        "sheet_id": 1010,
        "frame": {
          "x": 1,
          "y": 0,
          "w": 1,
          "h": 2
        },
        "number_of_frames": 1
      },
      "dialogues": [],
      "destination": null,
      "lock_type": "None",
      "display_conditions": [],
      "movement_directions": "None",
      "is_consumable": false,
      "contents": null,
      "is_invulnerable": true,
      "demands_attention": false,
      "after_dialogue": "Nothing"
    },
    {
      "id": 10909121,
      "frame": {
        "x": 8,
        "y": 1,
        "w": 1,
        "h": 1
      },
      "species_id": 1019,
      "entity_type": "Teleporter",
      "direction": "Down",
      "current_speed": 0.0,
      "sprite": {
        "sheet_id": 1010,
        "frame": {
          "x": 7,
          "y": 5,
          "w": 1,
          "h": 1
        },
        "number_of_frames": 1
      },
      "dialogues": [],
      "destination": {
        "world": 10909116,
        "x": 0,
        "y": 0,
        "direction": "Unknown"
      },
      "lock_type": "None",
      "display_conditions": [],
      "movement_directions": "None",
      "is_consumable": false,
      "contents": null,
      "is_invulnerable": true,
      "demands_attention": false,
      "after_dialogue": "Nothing"
    },
    {
      "id": 11962592,
      "frame": {
        "x": 1,
        "y": 1,
        "w": 2,
        "h": 2
      },
      "species_id": 1092,
      "entity_type": "StaticObject",
      "direction": "Down",
      "current_speed": 0.0,
      "sprite": {
        "sheet_id": 1010,
        "frame": {
          "x": 2,
          "y": 12,
          "w": 2,
          "h": 2
        },
        "number_of_frames": 1
      },
      "dialogues": [],
      "destination": null,
      "lock_type": "None",
      "display_conditions": [],
      "movement_directions": "None",
      "is_consumable": false,
      "contents": null,
      "is_invulnerable": false,
      "demands_attention": false,
      "after_dialogue": "Nothing"
    },
    {
      "id": 11962593,
      "frame": {
        "x": 3,
        "y": 1,
        "w": 2,
        "h": 2
      },
      "species_id": 1092,
      "entity_type": "StaticObject",
      "direction": "Down",
      "current_speed": 0.0,
      "sprite": {
        "sheet_id": 1010,
        "frame": {
          "x": 2,
          "y": 12,
          "w": 2,
          "h": 2
        },
        "number_of_frames": 1
      },
      "dialogues": [],
      "destination": null,
      "lock_type": "None",
      "display_conditions": [],
      "movement_directions": "None",
      "is_consumable": false,
      "contents": null,
      "is_invulnerable": false,
      "demands_attention": false,
      "after_dialogue": "Nothing"
    },
    {
      "id": 11962594,
      "frame": {
        "x": 10,
        "y": 1,
        "w": 1,
        "h": 2
      },
      "species_id": 1039,
      "entity_type": "StaticObject",
      "direction": "Down",
      "current_speed": 0.0,
      "sprite": {
        "sheet_id": 1010,
        "frame": {
          "x": 1,
          "y": 10,
          "w": 1,
          "h": 2
        },
        "number_of_frames": 1
      },
      "dialogues": [],
      "destination": null,
      "lock_type": "None",
      "display_conditions": [],
      "movement_directions": "None",
      "is_consumable": false,
      "contents": null,
      "is_invulnerable": false,
      "demands_attention": false,
      "after_dialogue": "Nothing"
    },
    {
      "id": 11962595,
      "frame": {
        "x": 10,
        "y": 2,
        "w": 1,
        "h": 2
      },
      "species_id": 1039,
      "entity_type": "StaticObject",
      "direction": "Down",
      "current_speed": 0.0,
      "sprite": {
        "sheet_id": 1010,
        "frame": {
          "x": 1,
          "y": 10,
          "w": 1,
          "h": 2
        },
        "number_of_frames": 1
      },
      "dialogues": [],
      "destination": null,
      "lock_type": "None",
      "display_conditions": [],
      "movement_directions": "None",
      "is_consumable": false,
      "contents": null,
      "is_invulnerable": false,
      "demands_attention": false,
      "after_dialogue": "Nothing"
    },
    {
      "id": 11962596,
      "frame": {
        "x": 10,
        "y": 3,
        "w": 1,
        "h": 2
      },
      "species_id": 1039,
      "entity_type": "StaticObject",
      "direction": "Down",
      "current_speed": 0.0,
      "sprite": {
        "sheet_id": 1010,
        "frame": {
          "x": 1,
          "y": 10,
          "w": 1,
          "h": 2
        },
        "number_of_frames": 1
      },
      "dialogues": [],
      "destination": null,
      "lock_type": "None",
      "display_conditions": [],
      "movement_directions": "None",
      "is_consumable": false,
      "contents": null,
      "is_invulnerable": false,
      "demands_attention": false,
      "after_dialogue": "Nothing"
    },
    {
      "id": 11962597,
      "frame": {
        "x": 10,
        "y": 4,
        "w": 1,
        "h": 2
      },
      "species_id": 1039,
      "entity_type": "StaticObject",
      "direction": "Down",
      "current_speed": 0.0,
      "sprite": {
        "sheet_id": 1010,
        "frame": {
          "x": 1,
          "y": 10,
          "w": 1,
          "h": 2
        },
        "number_of_frames": 1
      },
      "dialogues": [],
      "destination": null,
      "lock_type": "None",
      "display_conditions": [],
      "movement_directions": "None",
      "is_consumable": false,
      "contents": null,
      "is_invulnerable": false,
      "demands_attention": false,
      "after_dialogue": "Nothing"
    },
    {
      "id": 11962598,
      "frame": {
        "x": 10,
        "y": 5,
        "w": 1,
        "h": 2
      },
      "species_id": 1039,
      "entity_type": "StaticObject",
      "direction": "Down",
      "current_speed": 0.0,
      "sprite": {
        "sheet_id": 1010,
        "frame": {
          "x": 1,
          "y": 10,
          "w": 1,
          "h": 2
        },
        "number_of_frames": 1
      },
      "dialogues": [],
      "destination": null,
      "lock_type": "None",
      "display_conditions": [],
      "movement_directions": "None",
      "is_consumable": false,
      "contents": null,
      "is_invulnerable": false,
      "demands_attention": false,
      "after_dialogue": "Nothing"
    },
    {
      "id": 11962599,
      "frame": {
        "x": 10,
        "y": 6,
        "w": 1,
        "h": 2
      },
      "species_id": 1039,
      "entity_type": "StaticObject",
      "direction": "Down",
      "current_speed": 0.0,
      "sprite": {
        "sheet_id": 1010,
        "frame": {
          "x": 1,
          "y": 10,
          "w": 1,
          "h": 2
        },
        "number_of_frames": 1
      },
      "dialogues": [],
      "destination": null,
      "lock_type": "None",
      "display_conditions": [],
      "movement_directions": "None",
      "is_consumable": false,
      "contents": null,
      "is_invulnerable": false,
      "demands_attention": false,
      "after_dialogue": "Nothing"
    },
    {
      "id": 11962600,
      "frame": {
        "x": 9,
        "y": 1,
        "w": 1,
        "h": 2
      },
      "species_id": 1039,
      "entity_type": "StaticObject",
      "direction": "Down",
      "current_speed": 0.0,
      "sprite": {
        "sheet_id": 1010,
        "frame": {
          "x": 1,
          "y": 10,
          "w": 1,
          "h": 2
        },
        "number_of_frames": 1
      },
      "dialogues": [],
      "destination": null,
      "lock_type": "None",
      "display_conditions": [],
      "movement_directions": "None",
      "is_consumable": false,
      "contents": null,
      "is_invulnerable": false,
      "demands_attention": false,
      "after_dialogue": "Nothing"
    },
    {
      "id": 11962601,
      "frame": {
        "x": 9,
        "y": 3,
        "w": 1,
        "h": 2
      },
      "species_id": 1039,
      "entity_type": "StaticObject",
      "direction": "Down",
      "current_speed": 0.0,
      "sprite": {
        "sheet_id": 1010,
        "frame": {
          "x": 1,
          "y": 10,
          "w": 1,
          "h": 2
        },
        "number_of_frames": 1
      },
      "dialogues": [],
      "destination": null,
      "lock_type": "None",
      "display_conditions": [],
      "movement_directions": "None",
      "is_consumable": false,
      "contents": null,
      "is_invulnerable": false,
      "demands_attention": false,
      "after_dialogue": "Nothing"
    },
    {
      "id": 11962602,
      "frame": {
        "x": 9,
        "y": 2,
        "w": 1,
        "h": 2
      },
      "species_id": 1039,
      "entity_type": "StaticObject",
      "direction": "Down",
      "current_speed": 0.0,
      "sprite": {
        "sheet_id": 1010,
        "frame": {
          "x": 1,
          "y": 10,
          "w": 1,
          "h": 2
        },
        "number_of_frames": 1
      },
      "dialogues": [],
      "destination": null,
      "lock_type": "None",
      "display_conditions": [],
      "movement_directions": "None",
      "is_consumable": false,
      "contents": null,
      "is_invulnerable": false,
      "demands_attention": false,
      "after_dialogue": "Nothing"
    },
    {
      "id": 11962603,
      "frame": {
        "x": 9,
        "y": 4,
        "w": 1,
        "h": 2
      },
      "species_id": 1039,
      "entity_type": "StaticObject",
      "direction": "Down",
      "current_speed": 0.0,
      "sprite": {
        "sheet_id": 1010,
        "frame": {
          "x": 1,
          "y": 10,
          "w": 1,
          "h": 2
        },
        "number_of_frames": 1
      },
      "dialogues": [],
      "destination": null,
      "lock_type": "None",
      "display_conditions": [],
      "movement_directions": "None",
      "is_consumable": false,
      "contents": null,
      "is_invulnerable": false,
      "demands_attention": false,
      "after_dialogue": "Nothing"
    },
    {
      "id": 11962604,
      "frame": {
        "x": 9,
        "y": 5,
        "w": 1,
        "h": 2
      },
      "species_id": 1039,
      "entity_type": "StaticObject",
      "direction": "Down",
      "current_speed": 0.0,
      "sprite": {
        "sheet_id": 1010,
        "frame": {
          "x": 1,
          "y": 10,
          "w": 1,
          "h": 2
        },
        "number_of_frames": 1
      },
      "dialogues": [],
      "destination": null,
      "lock_type": "None",
      "display_conditions": [],
      "movement_directions": "None",
      "is_consumable": false,
      "contents": null,
      "is_invulnerable": false,
      "demands_attention": false,
      "after_dialogue": "Nothing"
    },
    {
      "id": 11962605,
      "frame": {
        "x": 9,
        "y": 6,
        "w": 1,
        "h": 2
      },
      "species_id": 1039,
      "entity_type": "StaticObject",
      "direction": "Down",
      "current_speed": 0.0,
      "sprite": {
        "sheet_id": 1010,
        "frame": {
          "x": 1,
          "y": 10,
          "w": 1,
          "h": 2
        },
        "number_of_frames": 1
      },
      "dialogues": [],
      "destination": null,
      "lock_type": "None",
      "display_conditions": [],
      "movement_directions": "None",
      "is_consumable": false,
      "contents": null,
      "is_invulnerable": false,
      "demands_attention": false,
      "after_dialogue": "Nothing"
    },
    {
      "id": 11962606,
      "frame": {
        "x": 7,
        "y": 1,
        "w": 1,
        "h": 2
      },
      "species_id": 1039,
      "entity_type": "StaticObject",
      "direction": "Down",
      "current_speed": 0.0,
      "sprite": {
        "sheet_id": 1010,
        "frame": {
          "x": 1,
          "y": 10,
          "w": 1,
          "h": 2
        },
        "number_of_frames": 1
      },
      "dialogues": [],
      "destination": null,
      "lock_type": "None",
      "display_conditions": [],
      "movement_directions": "None",
      "is_consumable": false,
      "contents": null,
      "is_invulnerable": false,
      "demands_attention": false,
      "after_dialogue": "Nothing"
    },
    {
      "id": 11962607,
      "frame": {
        "x": 6,
        "y": 1,
        "w": 1,
        "h": 2
      },
      "species_id": 1039,
      "entity_type": "StaticObject",
      "direction": "Down",
      "current_speed": 0.0,
      "sprite": {
        "sheet_id": 1010,
        "frame": {
          "x": 1,
          "y": 10,
          "w": 1,
          "h": 2
        },
        "number_of_frames": 1
      },
      "dialogues": [],
      "destination": null,
      "lock_type": "None",
      "display_conditions": [],
      "movement_directions": "None",
      "is_consumable": false,
      "contents": null,
      "is_invulnerable": false,
      "demands_attention": false,
      "after_dialogue": "Nothing"
    },
    {
      "id": 11962608,
      "frame": {
        "x": 5,
        "y": 1,
        "w": 1,
        "h": 2
      },
      "species_id": 1039,
      "entity_type": "StaticObject",
      "direction": "Down",
      "current_speed": 0.0,
      "sprite": {
        "sheet_id": 1010,
        "frame": {
          "x": 1,
          "y": 10,
          "w": 1,
          "h": 2
        },
        "number_of_frames": 1
      },
      "dialogues": [],
      "destination": null,
      "lock_type": "None",
      "display_conditions": [],
      "movement_directions": "None",
      "is_consumable": false,
      "contents": null,
      "is_invulnerable": false,
      "demands_attention": false,
      "after_dialogue": "Nothing"
    },
    {
      "id": 11962609,
      "frame": {
        "x": 1,
        "y": 6,
        "w": 1,
        "h": 2
      },
      "species_id": 1039,
      "entity_type": "StaticObject",
      "direction": "Down",
      "current_speed": 0.0,
      "sprite": {
        "sheet_id": 1010,
        "frame": {
          "x": 1,
          "y": 10,
          "w": 1,
          "h": 2
        },
        "number_of_frames": 1
      },
      "dialogues": [],
      "destination": null,
      "lock_type": "None",
      "display_conditions": [],
      "movement_directions": "None",
      "is_consumable": false,
      "contents": null,
      "is_invulnerable": false,
      "demands_attention": false,
      "after_dialogue": "Nothing"
    },
    {
      "id": 11962610,
      "frame": {
        "x": 2,
        "y": 6,
        "w": 1,
        "h": 2
      },
      "species_id": 1039,
      "entity_type": "StaticObject",
      "direction": "Down",
      "current_speed": 0.0,
      "sprite": {
        "sheet_id": 1010,
        "frame": {
          "x": 1,
          "y": 10,
          "w": 1,
          "h": 2
        },
        "number_of_frames": 1
      },
      "dialogues": [],
      "destination": null,
      "lock_type": "None",
      "display_conditions": [],
      "movement_directions": "None",
      "is_consumable": false,
      "contents": null,
      "is_invulnerable": false,
      "demands_attention": false,
      "after_dialogue": "Nothing"
    },
    {
      "id": 11962611,
      "frame": {
        "x": 3,
        "y": 6,
        "w": 1,
        "h": 2
      },
      "species_id": 1039,
      "entity_type": "StaticObject",
      "direction": "Down",
      "current_speed": 0.0,
      "sprite": {
        "sheet_id": 1010,
        "frame": {
          "x": 1,
          "y": 10,
          "w": 1,
          "h": 2
        },
        "number_of_frames": 1
      },
      "dialogues": [],
      "destination": null,
      "lock_type": "None",
      "display_conditions": [],
      "movement_directions": "None",
      "is_consumable": false,
      "contents": null,
      "is_invulnerable": false,
      "demands_attention": false,
      "after_dialogue": "Nothing"
    },
    {
      "id": 11962612,
      "frame": {
        "x": 1,
        "y": 5,
        "w": 1,
        "h": 2
      },
      "species_id": 1039,
      "entity_type": "StaticObject",
      "direction": "Down",
      "current_speed": 0.0,
      "sprite": {
        "sheet_id": 1010,
        "frame": {
          "x": 1,
          "y": 10,
          "w": 1,
          "h": 2
        },
        "number_of_frames": 1
      },
      "dialogues": [],
      "destination": null,
      "lock_type": "None",
      "display_conditions": [],
      "movement_directions": "None",
      "is_consumable": false,
      "contents": null,
      "is_invulnerable": false,
      "demands_attention": false,
      "after_dialogue": "Nothing"
    },
    {
      "id": 11962615,
      "frame": {
        "x": 5,
        "y": 4,
        "w": 1,
        "h": 1
      },
      "species_id": 1014,
      "entity_type": "StaticObject",
      "direction": "Down",
      "current_speed": 0.0,
      "sprite": {
        "sheet_id": 1010,
        "frame": {
          "x": 3,
          "y": 3,
          "w": 1,
          "h": 1
        },
        "number_of_frames": 1
      },
      "dialogues": [],
      "destination": null,
      "lock_type": "None",
      "display_conditions": [],
      "movement_directions": "None",
      "is_consumable": false,
      "contents": null,
      "is_invulnerable": true,
      "demands_attention": false,
      "after_dialogue": "Nothing"
    },
    {
      "id": 11962614,
      "frame": {
        "x": 4,
        "y": 4,
        "w": 1,
        "h": 1
      },
      "species_id": 1014,
      "entity_type": "StaticObject",
      "direction": "Down",
      "current_speed": 0.0,
      "sprite": {
        "sheet_id": 1010,
        "frame": {
          "x": 3,
          "y": 3,
          "w": 1,
          "h": 1
        },
        "number_of_frames": 1
      },
      "dialogues": [],
      "destination": null,
      "lock_type": "None",
      "display_conditions": [],
      "movement_directions": "None",
      "is_consumable": false,
      "contents": null,
      "is_invulnerable": true,
      "demands_attention": false,
      "after_dialogue": "Nothing"
    },
    {
      "id": 11962617,
      "frame": {
        "x": 4,
        "y": 6,
        "w": 1,
        "h": 1
      },
      "species_id": 1014,
      "entity_type": "StaticObject",
      "direction": "Down",
      "current_speed": 0.0,
      "sprite": {
        "sheet_id": 1010,
        "frame": {
          "x": 3,
          "y": 3,
          "w": 1,
          "h": 1
        },
        "number_of_frames": 1
      },
      "dialogues": [],
      "destination": null,
      "lock_type": "None",
      "display_conditions": [],
      "movement_directions": "None",
      "is_consumable": false,
      "contents": null,
      "is_invulnerable": true,
      "demands_attention": false,
      "after_dialogue": "Nothing"
    },
    {
      "id": 11962618,
      "frame": {
        "x": 5,
        "y": 6,
        "w": 1,
        "h": 1
      },
      "species_id": 1014,
      "entity_type": "StaticObject",
      "direction": "Down",
      "current_speed": 0.0,
      "sprite": {
        "sheet_id": 1010,
        "frame": {
          "x": 3,
          "y": 3,
          "w": 1,
          "h": 1
        },
        "number_of_frames": 1
      },
      "dialogues": [],
      "destination": null,
      "lock_type": "None",
      "display_conditions": [],
      "movement_directions": "None",
      "is_consumable": false,
      "contents": null,
      "is_invulnerable": true,
      "demands_attention": false,
      "after_dialogue": "Nothing"
    },
    {
      "id": 11962619,
      "frame": {
        "x": 3,
        "y": 5,
        "w": 1,
        "h": 1
      },
      "species_id": 1014,
      "entity_type": "StaticObject",
      "direction": "Down",
      "current_speed": 0.0,
      "sprite": {
        "sheet_id": 1010,
        "frame": {
          "x": 3,
          "y": 3,
          "w": 1,
          "h": 1
        },
        "number_of_frames": 1
      },
      "dialogues": [],
      "destination": null,
      "lock_type": "None",
      "display_conditions": [],
      "movement_directions": "None",
      "is_consumable": false,
      "contents": null,
      "is_invulnerable": true,
      "demands_attention": false,
      "after_dialogue": "Nothing"
    },
    {
      "id": 11962620,
      "frame": {
        "x": 6,
        "y": 5,
        "w": 1,
        "h": 1
      },
      "species_id": 1014,
      "entity_type": "StaticObject",
      "direction": "Down",
      "current_speed": 0.0,
      "sprite": {
        "sheet_id": 1010,
        "frame": {
          "x": 3,
          "y": 3,
          "w": 1,
          "h": 1
        },
        "number_of_frames": 1
      },
      "dialogues": [],
      "destination": null,
      "lock_type": "None",
      "display_conditions": [],
      "movement_directions": "None",
      "is_consumable": false,
      "contents": null,
      "is_invulnerable": true,
      "demands_attention": false,
      "after_dialogue": "Nothing"
    },
    {
      "id": 11962621,
      "frame": {
        "x": 4,
        "y": 4,
        "w": 2,
        "h": 2
      },
      "species_id": 1016,
      "entity_type": "StaticObject",
      "direction": "Down",
      "current_speed": 0.0,
      "sprite": {
        "sheet_id": 1010,
        "frame": {
          "x": 4,
          "y": 0,
          "w": 2,
          "h": 2
        },
        "number_of_frames": 1
      },
      "dialogues": [],
      "destination": null,
      "lock_type": "None",
      "display_conditions": [],
      "movement_directions": "None",
      "is_consumable": false,
      "contents": null,
      "is_invulnerable": true,
      "demands_attention": false,
      "after_dialogue": "Nothing"
    },
    {
      "id": 11962622,
      "frame": {
        "x": 4,
        "y": 5,
        "w": 1,
        "h": 1
      },
      "species_id": 6002,
      "entity_type": "StaticObject",
      "direction": "Down",
      "current_speed": 0.0,
      "sprite": {
        "sheet_id": 1012,
        "frame": {
          "x": 0,
          "y": 6,
          "w": 1,
          "h": 1
        },
        "number_of_frames": 8
      },
      "dialogues": [],
      "destination": null,
      "lock_type": "None",
      "display_conditions": [],
      "movement_directions": "None",
      "is_consumable": false,
      "contents": "lore.016.silver_vein_chronicles",
      "is_invulnerable": true,
      "demands_attention": false,
      "after_dialogue": "Nothing"
    }
  ],
  "is_interior": true,
  "light_conditions": "Day",
  "cutscenes": []
}